microversion_parse/__init__.py
microversion_parse/middleware.py
microversion_parse/py.typed
microversion_parse/tests/__init__.py
microversion_parse/tests/test_extract_version.py
microversion_parse/tests/test_get_version.py
microversion_parse/tests/test_headers_from_wsgi_environ.py
microversion_parse/tests/test_middleware.py
microversion_parse/tests/test_webob.py
microversion_parse/tests/gabbits/middleware.yaml
microversion_parse/tests/gabbits/simple.yaml
microversion_parse-2.1.0.dist-info/AUTHORS
microversion_parse-2.1.0.dist-info/LICENSE
microversion_parse-2.1.0.dist-info/METADATA
microversion_parse-2.1.0.dist-info/WHEEL
microversion_parse-2.1.0.dist-info/pbr.json
microversion_parse-2.1.0.dist-info/top_level.txt
microversion_parse-2.1.0.dist-info/RECORD
